.svnignore
CHANGES.txt
CONTRIBUTORS.txt
README.txt
setup.cfg
setup.py
docs/HISTORY.txt
docs/INSTALL.txt
docs/LICENSE.EUPL
docs/LICENSE.GPL
docs/LICENSE.txt
slc/__init__.py
slc.quickchange.egg-info/PKG-INFO
slc.quickchange.egg-info/SOURCES.txt
slc.quickchange.egg-info/dependency_links.txt
slc.quickchange.egg-info/entry_points.txt
slc.quickchange.egg-info/namespace_packages.txt
slc.quickchange.egg-info/not-zip-safe
slc.quickchange.egg-info/requires.txt
slc.quickchange.egg-info/top_level.txt
slc/quickchange/README.txt
slc/quickchange/__init__.py
slc/quickchange/configure.zcml
slc/quickchange/tests.py
slc/quickchange/browser/__init__.py
slc/quickchange/browser/configure.zcml
slc/quickchange/browser/searchreplace.pt
slc/quickchange/browser/searchreplace.py
slc/quickchange/profiles/default/actions.xml
slc/quickchange/profiles/default/metadata.xml