Metadata-Version: 1.0
Name: slc.quickchange
Version: 2.0
Summary: A tool that adds Search and Replace functionality for the content of your objects
Home-page: https://svn.syslab.com/svn/syslabcom/slc.quickchange/
Author: Syslab.com GmbH
Author-email: info@syslab.com
License: GPL + EUPL
Keywords: change batch quickchange search replace regex linguaplone
Platform: UNKNOWN
Classifier: Framework :: Plone
Classifier: Framework :: Zope2
Classifier: Framework :: Zope3
Classifier: Programming Language :: Python
Classifier: Topic :: Software Development :: Libraries :: Python Modules
Classifier: License :: OSI Approved :: GNU General Public License (GPL)
Classifier: License :: OSI Approved :: European Union Public Licence 1.1 (EUPL 1.1)
